asyncspinner/__init__.py
asyncspinner/__main__.py
asyncspinner/styles.py
asyncspinner-0.1.dist-info/LICENSE
asyncspinner-0.1.dist-info/METADATA
asyncspinner-0.1.dist-info/WHEEL
asyncspinner-0.1.dist-info/top_level.txt
asyncspinner-0.1.dist-info/RECORD
