Metadata-Version: 2.1
Name: asyncspinner
Version: 0.1
Summary: Little graphic to show user that something is waited for when a progress bar is overkill, or the progress is unknown.
Home-page: UNKNOWN
License: UNKNOWN
Project-URL: Source Code, https://github.com/Hegdahl/asyncspinner
Platform: UNKNOWN
Classifier: License :: OSI Approved :: MIT License
Requires-Dist: colorama
Requires-Dist: cursor
